rug/__init__.py
rug/alphaquery.py
rug/barchart.py
rug/base.py
rug/etfdb.py
rug/exceptions.py
rug/finviz.py
rug/stockanalysis.py
rug/stocktwits.py
rug/tipranks.py
rug-0.13.1.dist-info/licenses/LICENSE
rug-0.13.1.dist-info/METADATA
rug-0.13.1.dist-info/WHEEL
rug-0.13.1.dist-info/top_level.txt
rug-0.13.1.dist-info/RECORD
