Metadata-Version: 2.4
Name: rug
Version: 0.13.1
Summary: Library for fetching various stock data from the internet (official and unofficial APIs).
Author: Pavel Hrdina
License-Expression: MIT
Project-URL: Homepage, https://gitlab.com/imn1/rug
Project-URL: Repository, https://gitlab.com/imn1/rug
Project-URL: Documentation, https://rug.readthedocs.io/en/latest/
Classifier: Programming Language :: Python :: 3.13
Classifier: Programming Language :: Python :: 3 :: Only
Classifier: Intended Audience :: Developers
Classifier: Topic :: Software Development :: Libraries
Requires-Python: <4,>=3.13
License-File: LICENSE
Requires-Dist: cloudscraper
Requires-Dist: requests>=2.32.3
Dynamic: license-file
